vsc_ed-0.0.2.dist-info/METADATA
vsc_ed-0.0.2.dist-info/WHEEL
vsc_ed-0.0.2.dist-info/entry_points.txt
vsc_ed.py
vsc_ed-0.0.2.dist-info/RECORD
