Metadata-Version: 2.1
Name: vsc-ed
Version: 0.0.2
License: MIT
Requires-Python: >=3.10
Requires-Dist: httpx>=0.24.1
Requires-Dist: beautifulsoup4>=4.12.2
Requires-Dist: packaging>=23.1
